synthera/__init__.py
synthera/chartconfig.py
synthera/client.py
synthera/fixed_income.py
synthera/protocols.py
synthera/py.typed
synthera/utils.py
synthera-0.2.7.dist-info/METADATA
synthera-0.2.7.dist-info/WHEEL
synthera-0.2.7.dist-info/licenses/LICENSE
synthera-0.2.7.dist-info/RECORD
