Metadata-Version: 2.4
Name: synthera
Version: 0.2.7
Summary: Python client for Synthera AI API
Author: Synthera AI
License-File: LICENSE
Classifier: Development Status :: 4 - Beta
Classifier: License :: Other/Proprietary License
Classifier: Operating System :: OS Independent
Classifier: Programming Language :: Python :: 3
Requires-Python: >=3.9
Requires-Dist: httpx>=0.28.1
Requires-Dist: matplotlib>=3.8
Requires-Dist: numpy>=1.26.4
Requires-Dist: pandas>=2.1.2
Requires-Dist: pyarrow>=15.0.2
Requires-Dist: pydantic>=2.10.6
Requires-Dist: tenacity>=9.0.0
